Metadata-Version: 1.2
Name: PassportSDK
Version: 0.0.6
Summary: SDK of passport-micro-service
Home-page: UNKNOWN
Author: NoahWang
Author-email: 234082230@qq.com
Maintainer: noahwang
Maintainer-email: 234082230@qq.com
License: UNKNOWN
Platform: UNKNOWN
